CHANGES.rst
CONTRIBUTORS.rst
DEVELOP.rst
LICENSE.GPL
LICENSE.rst
MANIFEST.in
README.rst
setup.cfg
setup.py
docs/index.rst
src/collective/__init__.py
src/collective.faceted.map.egg-info/PKG-INFO
src/collective.faceted.map.egg-info/SOURCES.txt
src/collective.faceted.map.egg-info/dependency_links.txt
src/collective.faceted.map.egg-info/entry_points.txt
src/collective.faceted.map.egg-info/namespace_packages.txt
src/collective.faceted.map.egg-info/not-zip-safe
src/collective.faceted.map.egg-info/requires.txt
src/collective.faceted.map.egg-info/top_level.txt
src/collective/faceted/__init__.py
src/collective/faceted/map/__init__.py
src/collective/faceted/map/configure.zcml
src/collective/faceted/map/interfaces.py
src/collective/faceted/map/permissions.zcml
src/collective/faceted/map/setuphandlers.py
src/collective/faceted/map/testing.py
src/collective/faceted/map/testing.zcml
src/collective/faceted/map/upgrades.py
src/collective/faceted/map/upgrades.zcml
src/collective/faceted/map/utils.py
src/collective/faceted/map/browser/__init__.py
src/collective/faceted/map/browser/configure.zcml
src/collective/faceted/map/browser/map.pt
src/collective/faceted/map/browser/map.py
src/collective/faceted/map/browser/mapviewlet.pt
src/collective/faceted/map/browser/view.py
src/collective/faceted/map/browser/viewlet.py
src/collective/faceted/map/browser/overrides/.gitkeep
src/collective/faceted/map/browser/static/.gitkeep
src/collective/faceted/map/locales/README.rst
src/collective/faceted/map/locales/__init__.py
src/collective/faceted/map/locales/collective.faceted.map.pot
src/collective/faceted/map/locales/update.py
src/collective/faceted/map/locales/update.sh
src/collective/faceted/map/locales/en/LC_MESSAGES/collective.faceted.map.mo
src/collective/faceted/map/locales/en/LC_MESSAGES/collective.faceted.map.po
src/collective/faceted/map/locales/fr/LC_MESSAGES/collective.faceted.map.mo
src/collective/faceted/map/locales/fr/LC_MESSAGES/collective.faceted.map.po
src/collective/faceted/map/profiles/default/browserlayer.xml
src/collective/faceted/map/profiles/default/catalog.xml
src/collective/faceted/map/profiles/default/metadata.xml
src/collective/faceted/map/profiles/default/registry.xml
src/collective/faceted/map/profiles/default/rolemap.xml
src/collective/faceted/map/profiles/uninstall/browserlayer.xml
src/collective/faceted/map/tests/__init__.py
